pytest_trepan/__init__.py
pytest_trepan/plugin.py
pytest_trepan/version.py
pytest_trepan-3.1.0.dist-info/licenses/LICENSE
pytest_trepan-3.1.0.dist-info/METADATA
pytest_trepan-3.1.0.dist-info/WHEEL
pytest_trepan-3.1.0.dist-info/entry_points.txt
pytest_trepan-3.1.0.dist-info/top_level.txt
pytest_trepan-3.1.0.dist-info/RECORD
